odc/stac/__init__.py
odc/stac/_mdtools.py
odc/stac/_stac_load.py
odc/stac/model.py
odc/stac/py.typed
odc/stac/bench/__init__.py
odc/stac/bench/__main__.py
odc/stac/bench/_cli.py
odc/stac/bench/_prepare.py
odc/stac/bench/_report.py
odc/stac/bench/_run.py
odc/stac/testing/__init__.py
odc/stac/testing/stac.py
odc_stac-0.5.2.dist-info/licenses/LICENSE
odc_stac-0.5.2.dist-info/WHEEL
odc_stac-0.5.2.dist-info/METADATA
odc_stac-0.5.2.dist-info/RECORD
