Metadata-Version: 2.4
Name: odc-stac
Version: 0.5.2
Summary: Tooling for converting STAC metadata to ODC data model
Author: Open Data Cube
Maintainer: Open Data Cube
Requires-Python: >=3.10
Classifier: Intended Audience :: Developers
Classifier: Operating System :: OS Independent
Classifier: Programming Language :: Python :: 3.10
Classifier: Programming Language :: Python :: 3.11
Classifier: Programming Language :: Python :: 3.12
Classifier: Programming Language :: Python :: 3.13
Classifier: Topic :: Software Development :: Libraries :: Python Modules
Classifier: Topic :: Scientific/Engineering :: GIS
Classifier: Typing :: Typed
License-File: LICENSE
Requires-Dist: affine
Requires-Dist: odc-geo>=0.4.7
Requires-Dist: odc-loader>=0.6.4
Requires-Dist: rasterio>=1.0.0,!=1.3.0,!=1.3.1
Requires-Dist: dask[array]
Requires-Dist: numpy>=1.20.0
Requires-Dist: pandas
Requires-Dist: pystac>=1.0.0,<2
Requires-Dist: toolz
Requires-Dist: typing-extensions
Requires-Dist: xarray>=0.19
Requires-Dist: botocore ; extra == "botocore"
Requires-Dist: sphinx ; extra == "docs"
Requires-Dist: sphinx_rtd_theme ; extra == "docs"
Requires-Dist: nbsphinx ; extra == "docs"
Requires-Dist: sphinx-autodoc-typehints ; extra == "docs"
Requires-Dist: matplotlib-inline ; extra == "docs"
Requires-Dist: pandas ; extra == "docs"
Requires-Dist: distributed ; extra == "docs"
Requires-Dist: ipython ; extra == "docs"
Requires-Dist: ipykernel ; extra == "docs"
Requires-Dist: pytest ; extra == "test"
Requires-Dist: pytest-cov ; extra == "test"
Requires-Dist: pytest-timeout ; extra == "test"
Requires-Dist: pystac_client ; extra == "test"
Requires-Dist: distributed ; extra == "test"
Requires-Dist: geopandas ; extra == "test"
Requires-Dist: pytest ; extra == "test-all"
Requires-Dist: pytest-cov ; extra == "test-all"
Requires-Dist: pytest-timeout ; extra == "test-all"
Requires-Dist: pystac_client ; extra == "test-all"
Requires-Dist: distributed ; extra == "test-all"
Requires-Dist: geopandas ; extra == "test-all"
Requires-Dist: stackstac ; extra == "test-all"
Project-URL: Bug Reporting, https://github.com/opendatacube/odc-stac/issues
Project-URL: Documentation, https://odc-stac.readthedocs.io/en/latest/
Project-URL: Homepage, https://github.com/opendatacube/odc-stac/
Provides-Extra: botocore
Provides-Extra: docs
Provides-Extra: test
Provides-Extra: test-all
